pyMysterium/__init__.py
pyMysterium/endpoints.py
pyMysterium/errors.py
pyMysterium/main.py
pyMysterium/models.py
pyMysterium-0.0.18.dist-info/METADATA
pyMysterium-0.0.18.dist-info/WHEEL
pyMysterium-0.0.18.dist-info/top_level.txt
pyMysterium-0.0.18.dist-info/RECORD
